leaflock/__init__.py
leaflock/conversion.py
leaflock/database.py
leaflock/licenses.py
leaflock/py.typed
leaflock/alembic/alembic.ini
leaflock/alembic/env.py
leaflock/alembic/script.py.mako
leaflock/alembic/versions/055ce6e4083c_add_licenses_to_topics_and_activities.py
leaflock/alembic/versions/5daf3ef38aac_change_from_id_pk_to_guid_pk.py
leaflock/alembic/versions/7fd433c8e65b_ordered_lists.py
leaflock/alembic/versions/8a3fbf75e80b_change_from_module_to_topic.py
leaflock/alembic/versions/a034d08cbfd1_correctly_use_uuid_keys_in_join_table.py
leaflock/alembic/versions/a6446496220c_add_new_fields_to_textbook_defaults_to_.py
leaflock/alembic/versions/d3da9ab956d7_initial.py
leaflock/alembic/versions/f936aadf86f1_add_additional_source_author_reviewer_.py
leaflock/pydantic_models/__init__.py
leaflock/pydantic_models/activity.py
leaflock/pydantic_models/textbook.py
leaflock/pydantic_models/topic.py
leaflock/sqlalchemy_tables/__init__.py
leaflock/sqlalchemy_tables/activity.py
leaflock/sqlalchemy_tables/base.py
leaflock/sqlalchemy_tables/joins.py
leaflock/sqlalchemy_tables/textbook.py
leaflock/sqlalchemy_tables/topic.py
leaflock-0.3.3.dist-info/METADATA
leaflock-0.3.3.dist-info/WHEEL
leaflock-0.3.3.dist-info/licenses/LICENSE
leaflock-0.3.3.dist-info/RECORD
