Metadata-Version: 2.4
Name: leaflock
Version: 0.3.3
Summary: OELMs generative textbook definition.
Project-URL: Homepage, https://github.com/kalendar/leaflock
Project-URL: Issues, https://github.com/kalendar/leaflock/issues
Author-email: David Wiley <david.wiley@gmail.com>, Joshua Maddy <joshuadcmaddy@gmail.com>
License-Expression: AGPL-3.0-or-later
License-File: LICENSE
Classifier: Operating System :: OS Independent
Classifier: Programming Language :: Python :: 3
Requires-Python: >=3.13
Requires-Dist: alembic>=1.15.1
Requires-Dist: bidict>=0.23.1
Requires-Dist: dotenv>=0.9.9
Requires-Dist: pydantic>=2.10.6
Requires-Dist: sqlalchemy>=2.0.39
